{
    "cli": true,
    "target": "directory",
    "adapterName": "contactid",
    "title": "Contact ID",
    "description": "The protocol Contact ID used by alarm systems to communicate with central stations",
    "keywords": ["contactid", "lupusec", "alarm", "burglar"],
    "expert": "yes",
    "features": ["adapter"],
    "adminFeatures": [],
    "type": "alarm",
    "startMode": "daemon",
    "connectionType": "local",
    "dataSource": "push",
    "connectionIndicator": "yes",
    "language": "TypeScript",
    "nodeVersion": "20",
    "adminUi": "json",
    "tools": ["ESLint", "Prettier"],
    "releaseScript": "yes",
    "devServer": "no",
    "indentation": "Space (4)",
    "quotes": "single",
    "authorName": "Thorsten Stueben",
    "authorGithub": "schmupu",
    "authorEmail": "thorsten@stueben.de",
    "gitRemoteProtocol": "HTTPS",
    "gitCommit": "no",
    "defaultBranch": "master",
    "license": "MIT License",
    "dependabot": "yes",
    "creatorVersion": "2.6.5"
}
